{
  "firstSets": {
    "Program": [
      "epsilon",
      "int",
      "void"
    ],
    "DeclarationList": [
      "epsilon",
      "int",
      "void"
    ],
    "Declaration": [
      "int",
      "void"
    ],
    "DeclarationInitial": [
      "int",
      "void"
    ],
    "DeclarationPrime": [
      "(",
      ";",
      "["
    ],
    "VarDeclarationPrime": [
      ";",
      "["
    ],
    "FunDeclarationPrime": [
      "("
    ],
    "TypeSpecifier": [
      "int",
      "void"
    ],
    "Params": [
      "int",
      "void"
    ],
    "ParamList": [
      ",",
      "epsilon"
    ],
    "Param": [
      "int",
      "void"
    ],
    "ParamPrime": [
      "[",
      "epsilon"
    ],
    "CompoundStmt": [
      "{"
    ],
    "StatementList": [
      "epsilon",
      "{",
      "break",
      ";",
      "if",
      "while",
      "return",
      "ID",
      "+",
      "-",
      "(",
      "NUM"
    ],
    "Statement": [
      "{",
      "break",
      ";",
      "if",
      "while",
      "return",
      "ID",
      "+",
      "-",
      "(",
      "NUM"
    ],
    "ExpressionStmt": [
      "break",
      ";",
      "ID",
      "+",
      "-",
      "(",
      "NUM"
    ],
    "SelectionStmt": [
      "if"
    ],
    "IterationStmt": [
      "while"
    ],
    "ReturnStmt": [
      "return"
    ],
    "ReturnStmtPrime": [
      ";",
      "ID",
      "+",
      "-",
      "(",
      "NUM"
    ],
    "Expression": [
      "ID",
      "+",
      "-",
      "(",
      "NUM"
    ],
    "B": [
      "=",
      "[",
      "(",
      "epsilon"
    ],
    "H": [
      "=",
      "*",
      "epsilon"
    ],
    "SimpleExpressionZegond": [
      "+",
      "-",
      "(",
      "NUM"
    ],
    "SimpleExpressionPrime": [
      "(",
      "epsilon"
    ],
    "C": [
      "epsilon",
      "<",
      "=="
    ],
    "Relop": [
      "<",
      "=="
    ],
    "AdditiveExpression": [
      "+",
      "-",
      "(",
      "ID",
      "NUM"
    ],
    "AdditiveExpressionPrime": [
      "(",
      "epsilon"
    ],
    "AdditiveExpressionZegond": [
      "+",
      "-",
      "(",
      "NUM"
    ],
    "D": [
      "epsilon",
      "+",
      "-"
    ],
    "Addop": [
      "+",
      "-"
    ],
    "Term": [
      "+",
      "-",
      "(",
      "ID",
      "NUM"
    ],
    "TermPrime": [
      "(",
      "epsilon"
    ],
    "TermZegond": [
      "+",
      "-",
      "(",
      "NUM"
    ],
    "G": [
      "*",
      "epsilon"
    ],
    "Factor": [
      "(",
      "ID",
      "NUM"
    ],
    "VarCallPrime": [
      "(",
      "[",
      "epsilon"
    ],
    "VarPrime": [
      "[",
      "epsilon"
    ],
    "FactorZegond": [
      "(",
      "NUM"
    ],
    "Args": [
      "epsilon",
      "ID",
      "+",
      "-",
      "(",
      "NUM"
    ],
    "ArgList": [
      "ID",
      "+",
      "-",
      "(",
      "NUM"
    ],
    "ArgListPrime": [
      ",",
      "epsilon"
    ],
    "SignedFactor": [
      "+",
      "-",
      "(",
      "ID",
      "NUM"
    ],
    "SignedFactorPrime": [
      "(",
      "epsilon"
    ],
    "FactorPrime": [
      "(",
      "epsilon"
    ],
    "SignedFactorZegond": [
      "+",
      "-",
      "(",
      "NUM"
    ]
  },
  "followSets": {
    "Program": [
      "\u0000"
    ],
    "DeclarationList": [
      "\u0000",
      "epsilon",
      "{",
      "break",
      ";",
      "if",
      "while",
      "return",
      "ID",
      "+",
      "-",
      "(",
      "NUM"
    ],
    "Declaration": [
      "epsilon",
      "int",
      "void"
    ],
    "DeclarationInitial": [
      "(",
      ";",
      "[",
      "epsilon"
    ],
    "DeclarationPrime": [
      "epsilon",
      "int",
      "void"
    ],
    "VarDeclarationPrime": [
      "epsilon",
      "int",
      "void"
    ],
    "FunDeclarationPrime": [
      "epsilon",
      "int",
      "void"
    ],
    "TypeSpecifier": [
      "ID"
    ],
    "Params": [
      ")"
    ],
    "ParamList": [
      ")"
    ],
    "Param": [
      ",",
      "epsilon"
    ],
    "ParamPrime": [
      ",",
      "epsilon"
    ],
    "CompoundStmt": [
      "epsilon",
      "int",
      "void",
      "{",
      "break",
      ";",
      "if",
      "while",
      "return",
      "ID",
      "+",
      "-",
      "(",
      "NUM",
      "else"
    ],
    "StatementList": [
      "}"
    ],
    "Statement": [
      "epsilon",
      "{",
      "break",
      ";",
      "if",
      "while",
      "return",
      "ID",
      "+",
      "-",
      "(",
      "NUM",
      "else"
    ],
    "ExpressionStmt": [
      "epsilon",
      "{",
      "break",
      ";",
      "if",
      "while",
      "return",
      "ID",
      "+",
      "-",
      "(",
      "NUM",
      "else"
    ],
    "SelectionStmt": [
      "epsilon",
      "{",
      "break",
      ";",
      "if",
      "while",
      "return",
      "ID",
      "+",
      "-",
      "(",
      "NUM",
      "else"
    ],
    "IterationStmt": [
      "epsilon",
      "{",
      "break",
      ";",
      "if",
      "while",
      "return",
      "ID",
      "+",
      "-",
      "(",
      "NUM",
      "else"
    ],
    "ReturnStmt": [
      "epsilon",
      "{",
      "break",
      ";",
      "if",
      "while",
      "return",
      "ID",
      "+",
      "-",
      "(",
      "NUM",
      "else"
    ],
    "ReturnStmtPrime": [
      "epsilon",
      "{",
      "break",
      ";",
      "if",
      "while",
      "return",
      "ID",
      "+",
      "-",
      "(",
      "NUM",
      "else"
    ],
    "Expression": [
      ";",
      ")",
      "]",
      ",",
      "epsilon"
    ],
    "B": [
      ";",
      ")",
      "]",
      ",",
      "epsilon"
    ],
    "H": [
      ";",
      ")",
      "]",
      ",",
      "epsilon"
    ],
    "SimpleExpressionZegond": [
      ";",
      ")",
      "]",
      ",",
      "epsilon"
    ],
    "SimpleExpressionPrime": [
      ";",
      ")",
      "]",
      ",",
      "epsilon"
    ],
    "C": [
      ";",
      ")",
      "]",
      ",",
      "epsilon"
    ],
    "Relop": [
      "+",
      "-",
      "(",
      "ID",
      "NUM"
    ],
    "AdditiveExpression": [
      ";",
      ")",
      "]",
      ",",
      "epsilon"
    ],
    "AdditiveExpressionPrime": [
      "epsilon",
      "<",
      "=="
    ],
    "AdditiveExpressionZegond": [
      "epsilon",
      "<",
      "=="
    ],
    "D": [
      "epsilon",
      "<",
      "==",
      ";",
      ")",
      "]",
      ","
    ],
    "Addop": [
      "+",
      "-",
      "(",
      "ID",
      "NUM"
    ],
    "Term": [
      "epsilon",
      "+",
      "-"
    ],
    "TermPrime": [
      "epsilon",
      "+",
      "-"
    ],
    "TermZegond": [
      "epsilon",
      "+",
      "-"
    ],
    "G": [
      "epsilon",
      "+",
      "-"
    ],
    "Factor": [
      "*",
      "epsilon"
    ],
    "VarCallPrime": [
      "*",
      "epsilon"
    ],
    "VarPrime": [
      "*",
      "epsilon"
    ],
    "FactorZegond": [
      "*",
      "epsilon"
    ],
    "Args": [
      ")"
    ],
    "ArgList": [
      ")"
    ],
    "ArgListPrime": [
      ")"
    ],
    "SignedFactor": [
      "*",
      "epsilon"
    ],
    "SignedFactorPrime": [
      "*",
      "epsilon"
    ],
    "FactorPrime": [
      "*",
      "epsilon"
    ],
    "SignedFactorZegond": [
      "*",
      "epsilon"
    ]
  },
  "predictSets": {
    "1": [
      "epsilon",
      "int",
      "void"
    ],
    "2": [
      "int",
      "void"
    ],
    "3": [
      "epsilon"
    ],
    "4": [
      "int",
      "void"
    ],
    "5": [
      "int",
      "void"
    ],
    "6": [
      "("
    ],
    "7": [
      ";",
      "["
    ],
    "8": [
      ";"
    ],
    "9": [
      "["
    ],
    "10": [
      "("
    ],
    "11": [
      "int"
    ],
    "12": [
      "void"
    ],
    "13": [
      "int"
    ],
    "14": [
      "void"
    ],
    "15": [
      ","
    ],
    "16": [
      "epsilon"
    ],
    "17": [
      "int",
      "void"
    ],
    "18": [
      "["
    ],
    "19": [
      "epsilon"
    ],
    "20": [
      "{"
    ],
    "21": [
      "{",
      "break",
      ";",
      "if",
      "while",
      "return",
      "ID",
      "+",
      "-",
      "(",
      "NUM"
    ],
    "22": [
      "epsilon"
    ],
    "23": [
      "break",
      ";",
      "ID",
      "+",
      "-",
      "(",
      "NUM"
    ],
    "24": [
      "{"
    ],
    "25": [
      "if"
    ],
    "26": [
      "while"
    ],
    "27": [
      "return"
    ],
    "28": [
      "ID",
      "+",
      "-",
      "(",
      "NUM"
    ],
    "29": [
      "break"
    ],
    "30": [
      ";"
    ],
    "31": [
      "if"
    ],
    "32": [
      "while"
    ],
    "33": [
      "return"
    ],
    "34": [
      ";"
    ],
    "35": [
      "ID",
      "+",
      "-",
      "(",
      "NUM"
    ],
    "36": [
      "+",
      "-",
      "(",
      "NUM"
    ],
    "37": [
      "ID"
    ],
    "38": [
      "="
    ],
    "39": [
      "["
    ],
    "40": [
      "(",
      "epsilon"
    ],
    "41": [
      "="
    ],
    "42": [
      "*",
      "epsilon"
    ],
    "43": [
      "+",
      "-",
      "(",
      "NUM"
    ],
    "44": [
      "(",
      "epsilon"
    ],
    "45": [
      "<",
      "=="
    ],
    "46": [
      "epsilon"
    ],
    "47": [
      "<"
    ],
    "48": [
      "=="
    ],
    "49": [
      "+",
      "-",
      "(",
      "ID",
      "NUM"
    ],
    "50": [
      "(",
      "epsilon"
    ],
    "51": [
      "+",
      "-",
      "(",
      "NUM"
    ],
    "52": [
      "+",
      "-"
    ],
    "53": [
      "epsilon"
    ],
    "54": [
      "+"
    ],
    "55": [
      "-"
    ],
    "56": [
      "+",
      "-",
      "(",
      "ID",
      "NUM"
    ],
    "57": [
      "(",
      "epsilon"
    ],
    "58": [
      "+",
      "-",
      "(",
      "NUM"
    ],
    "59": [
      "*"
    ],
    "60": [
      "epsilon"
    ],
    "61": [
      "("
    ],
    "62": [
      "ID"
    ],
    "63": [
      "NUM"
    ],
    "64": [
      "("
    ],
    "65": [
      "[",
      "epsilon"
    ],
    "66": [
      "["
    ],
    "67": [
      "epsilon"
    ],
    "68": [
      "("
    ],
    "69": [
      "NUM"
    ],
    "70": [
      "ID",
      "+",
      "-",
      "(",
      "NUM"
    ],
    "71": [
      "epsilon"
    ],
    "72": [
      "ID",
      "+",
      "-",
      "(",
      "NUM"
    ],
    "73": [
      ","
    ],
    "74": [
      "epsilon"
    ],
    "75": [
      "+"
    ],
    "76": [
      "-"
    ],
    "77": [
      "(",
      "ID",
      "NUM"
    ],
    "78": [
      "(",
      "epsilon"
    ],
    "79": [
      "("
    ],
    "80": [
      "epsilon"
    ],
    "81": [
      "+"
    ],
    "82": [
      "-"
    ],
    "83": [
      "(",
      "NUM"
    ]
  }
}